cgekit/__init__.py
cgekit-0.1.1.dist-info/LICENSE.MD
cgekit-0.1.1.dist-info/WHEEL
cgekit-0.1.1.dist-info/METADATA
cgekit-0.1.1.dist-info/RECORD
