Metadata-Version: 2.1
Name: cgekit
Version: 0.1.1
Summary: Additional tools for the cgePy library
License: MIT
Author: catbox305
Requires-Python: >=3.8,<4.0
Classifier: License :: OSI Approved :: MIT License
Classifier: Programming Language :: Python :: 3
Classifier: Programming Language :: Python :: 3.8
Classifier: Programming Language :: Python :: 3.9
Classifier: Programming Language :: Python :: 3.10
Classifier: Programming Language :: Python :: 3.11
Requires-Dist: cgepy (>=0.6.3,<0.7.0)
